simppler/__init__.py
simppler/_version.py
simppler/basis.py
simppler/model.py
simppler/plot.py
simppler/utils.py
simppler-0.1.1.dist-info/METADATA
simppler-0.1.1.dist-info/WHEEL
simppler-0.1.1.dist-info/licenses/LICENSE
simppler-0.1.1.dist-info/RECORD
